cotainr/__init__.py
cotainr/__main__.py
cotainr/_version.py
cotainr/cli.py
cotainr/container.py
cotainr/pack.py
cotainr/tracing.py
cotainr/util.py
cotainr-2025.7.1.dist-info/METADATA
cotainr-2025.7.1.dist-info/WHEEL
cotainr-2025.7.1.dist-info/entry_points.txt
cotainr-2025.7.1.dist-info/licenses/LICENSE
cotainr-2025.7.1.dist-info/RECORD
