Metadata-Version: 2.4
Name: cotainr
Version: 2025.7.1
Summary: A user space Apptainer/Singularity container builder
Project-URL: Documentation, https://cotainr.readthedocs.io/en/stable/
Project-URL: Repository, https://github.com/DeiC-HPC/cotainr.git
Project-URL: Bug Tracker, https://github.com/DeiC-HPC/cotainr/issues
Project-URL: Changelog, https://cotainr.readthedocs.io/en/stable/release_notes/index.html
Author: Christian Schou Oxvig, René Løwe Jacobsen, Eske Christiansen, Joachim Sødequist, Tor Skovsgaard, Julius Roeder
Maintainer: DeiC HPC
License-Expression: EUPL-1.2
License-File: LICENSE
Keywords: apptainer,conda,container,hpc,singularity
Classifier: Development Status :: 5 - Production/Stable
Classifier: Intended Audience :: End Users/Desktop
Classifier: License :: OSI Approved :: European Union Public Licence 1.2 (EUPL 1.2)
Classifier: Programming Language :: Python :: 3
Classifier: Programming Language :: Python :: 3.9
Classifier: Programming Language :: Python :: 3.10
Classifier: Programming Language :: Python :: 3.11
Classifier: Programming Language :: Python :: 3.12
Classifier: Programming Language :: Python :: 3.13
Requires-Python: >=3.9
